stdqt6/__init__.py
stdqt6/_all.py
stdqt6/gen.py
stdqt6-0.0.1.dist-info/licenses/LICENSE
stdqt6-0.0.1.dist-info/METADATA
stdqt6-0.0.1.dist-info/WHEEL
stdqt6-0.0.1.dist-info/top_level.txt
stdqt6-0.0.1.dist-info/RECORD
