Metadata-Version: 2.4
Name: stdqt6
Version: 0.0.1
Summary: Include almost all modules and classes of PyQt6.
Home-page: https://github.com/MnlSmile/stdqt
Author: MnlSmile
Author-email: kedoukedou33@163.com
License-File: LICENSE
Requires-Dist: pyqt6
Requires-Dist: PyQt6-WebEngine
Dynamic: author
Dynamic: author-email
Dynamic: home-page
Dynamic: license-file
Dynamic: requires-dist
Dynamic: summary
